b3fileparser/__init__.py
b3fileparser/b3_meta_data.py
b3fileparser/b3parser.py
b3fileparser/b3parser_base.py
b3fileparser/b3parser_pandas.py
b3fileparser/b3parser_polars.py
b3fileparser-0.2.0.dist-info/LICENSE
b3fileparser-0.2.0.dist-info/METADATA
b3fileparser-0.2.0.dist-info/WHEEL
b3fileparser-0.2.0.dist-info/RECORD
