Metadata-Version: 2.1
Name: b3fileparser
Version: 0.2.0
Summary: A Python parser of Brazilian exchange B3 historical data files
License: MIT
Author: codigoquant
Author-email: codigoquant@gmail.com
Requires-Python: >=3.10,<4.0
Classifier: License :: OSI Approved :: MIT License
Classifier: Programming Language :: Python :: 3
Classifier: Programming Language :: Python :: 3.10
Classifier: Programming Language :: Python :: 3.11
Classifier: Programming Language :: Python :: 3.12
Requires-Dist: pandas (>=2.0,<3.0)
Requires-Dist: polars (>=0.20.29,<0.21.0)
